lala-0.4.dist-info/top_level.txt
lala-0.4.dist-info/METADATA
lala-0.4.dist-info/DESCRIPTION.rst
lala-0.4.dist-info/RECORD
lala-0.4.dist-info/WHEEL
lala-0.4.dist-info/metadata.json
lala/util.py
lala/bot.py
lala/pluginmanager.py
lala/version.py
lala/factory.py
lala/config.py
lala/__init__.py
lala/main.py
lala/plugins/down.py
lala/plugins/anime.py
lala/plugins/decide.py
lala/plugins/quotes.py
lala/plugins/calendar.py
lala/plugins/log.py
lala/plugins/httptitle.py
lala/plugins/base.py
lala/plugins/birthday.py
lala/plugins/last.py
lala/plugins/roulette.py
lala/plugins/__init__.py
lala/plugins/fortune.py
lala-0.3_29_g917e0f2.data/data/usr/share/doc/lala/config.example
twisted/plugins/lala_plugin.py
