Metadata-Version: 2.0
Name: lala
Version: 0.4
Summary: IRC bot based on the twisted framework
Home-page: ['http://github.com/mineo/lala']
Author: Wieland Hoffmann
Author-email: themineo@gmail.com
License: MIT
Download-URL: ['https://github.com/mineo/lala/tarball/master']
Platform: UNKNOWN
Classifier: Development Status :: 4 - Beta
Classifier: Environment :: Console
Classifier: Framework :: Twisted
Classifier: License :: OSI Approved :: MIT License
Classifier: Natural Language :: English
Classifier: Operating System :: OS Independent
Classifier: Programming Language :: Python :: 2.6
Classifier: Programming Language :: Python :: 2.7
Requires: Twisted
